odoo/addons/web_field_tooltip/README.rst
odoo/addons/web_field_tooltip/__init__.py
odoo/addons/web_field_tooltip/__manifest__.py
odoo/addons/web_field_tooltip/i18n/fr.po
odoo/addons/web_field_tooltip/i18n/it.po
odoo/addons/web_field_tooltip/i18n/web_field_tooltip.pot
odoo/addons/web_field_tooltip/migrations/17.0.1.0.0/post-migrate.py
odoo/addons/web_field_tooltip/models/__init__.py
odoo/addons/web_field_tooltip/models/base.py
odoo/addons/web_field_tooltip/models/ir_http.py
odoo/addons/web_field_tooltip/models/ir_model_fields_tooltip.py
odoo/addons/web_field_tooltip/models/res_users.py
odoo/addons/web_field_tooltip/readme/CONTRIBUTORS.md
odoo/addons/web_field_tooltip/readme/DESCRIPTION.md
odoo/addons/web_field_tooltip/readme/ROADMAP.md
odoo/addons/web_field_tooltip/readme/USAGE.md
odoo/addons/web_field_tooltip/security/ir_model_access.xml
odoo/addons/web_field_tooltip/security/res_groups.xml
odoo/addons/web_field_tooltip/static/description/icon.png
odoo/addons/web_field_tooltip/static/description/index.html
odoo/addons/web_field_tooltip/static/src/views/form/form_controller.esm.js
odoo/addons/web_field_tooltip/static/src/views/form/form_label.esm.js
odoo/addons/web_field_tooltip/static/src/views/form/form_label.xml
odoo/addons/web_field_tooltip/tests/__init__.py
odoo/addons/web_field_tooltip/tests/test_web_field_tooltip.py
odoo/addons/web_field_tooltip/views/ir_model_fields_tooltip.xml
odoo/addons/web_field_tooltip/views/res_users.xml
odoo_addon_web_field_tooltip-17.0.1.0.0.4.dist-info/METADATA
odoo_addon_web_field_tooltip-17.0.1.0.0.4.dist-info/WHEEL
odoo_addon_web_field_tooltip-17.0.1.0.0.4.dist-info/top_level.txt
odoo_addon_web_field_tooltip-17.0.1.0.0.4.dist-info/RECORD
